{
  "startTime": "2025-12-13T07:22:29.381Z",
  "strategy": "separated-endpoints",
  "updated": [
    "tom",
    "sarah",
    "wendy"
  ],
  "failed": [],
  "skipped": [],
  "details": {
    "tom": {
      "success": true,
      "matchCount": 268,
      "source": "worker",
      "dataHash": "d77f3bb94aaa"
    },
    "sarah": {
      "success": true,
      "matchCount": 307,
      "source": "worker",
      "dataHash": "88a3a7a09c90"
    },
    "wendy": {
      "success": true,
      "restored": true,
      "source": "backup",
      "recoveryDetails": {
        "recovered": true,
        "backupFile": "wendy-data-1765610566138.json",
        "timestamp": "2025-12-13T07:22:55.508Z"
      }
    }
  },
  "circuitBreakers": {
    "tom": {
      "state": "CLOSED",
      "failures": 0,
      "lastFailure": null
    },
    "sarah": {
      "state": "CLOSED",
      "failures": 0,
      "lastFailure": null
    },
    "wendy": {
      "state": "CLOSED",
      "failures": 0,
      "lastFailure": null
    }
  },
  "integrity": {
    "totalAttempted": 3,
    "successful": 2,
    "failed": 0,
    "recovered": 1
  },
  "endTime": "2025-12-13T07:22:56.008Z",
  "duration": 26627
}