{
  "startTime": "2025-11-24T12:22:03.129Z",
  "updated": [
    "sarah",
    "tom",
    "wendy"
  ],
  "failed": [],
  "skipped": [],
  "details": {
    "sarah": {
      "matchCount": 474,
      "source": "corsproxy.io",
      "success": true,
      "dataHash": "a1b38f362f881ce79f6a1238bf106db1"
    },
    "tom": {
      "matchCount": 835,
      "source": "corsproxy.io",
      "success": true,
      "dataHash": "980a241b777a086b098b0e38f234b9e4"
    },
    "wendy": {
      "matchCount": 101,
      "source": "9kilos-proxy.mandiyandiyakhonyana.workers.dev",
      "success": true,
      "dataHash": "916f6ec0bab72a48c478f3870a659e4f"
    }
  },
  "endTime": "2025-11-24T12:22:04.639Z",
  "duration": 1510
}