{
  "startTime": "2026-05-05T19:21:46.983Z",
  "strategy": "separated-endpoints",
  "updated": [
    "tom",
    "sarah",
    "wendy"
  ],
  "failed": [],
  "skipped": [],
  "details": {
    "tom": {
      "success": true,
      "restored": true,
      "source": "backup",
      "recoveryDetails": {
        "recovered": true,
        "backupFile": "tom-data-1778008921990.json",
        "timestamp": "2026-05-05T19:22:05.541Z"
      }
    },
    "sarah": {
      "success": true,
      "matchCount": 202,
      "source": "worker",
      "dataHash": "259c4a8e8679"
    },
    "wendy": {
      "success": true,
      "restored": true,
      "source": "backup",
      "recoveryDetails": {
        "recovered": true,
        "backupFile": "wendy-data-1778008927605.json",
        "timestamp": "2026-05-05T19:23:47.003Z"
      }
    }
  },
  "circuitBreakers": {
    "tom": {
      "state": "CLOSED",
      "failures": 0,
      "lastFailure": null
    },
    "sarah": {
      "state": "CLOSED",
      "failures": 0,
      "lastFailure": null
    },
    "wendy": {
      "state": "CLOSED",
      "failures": 0,
      "lastFailure": null
    }
  },
  "integrity": {
    "totalAttempted": 3,
    "successful": 1,
    "failed": 0,
    "recovered": 2
  },
  "endTime": "2026-05-05T19:23:47.503Z",
  "duration": 120520
}