{
  "startTime": "2025-11-24T07:14:54.278Z",
  "updated": [
    "sarah",
    "tom"
  ],
  "failed": [],
  "skipped": [],
  "details": {
    "sarah": {
      "matchCount": 437,
      "source": "corsproxy.io",
      "success": true,
      "dataHash": "7ed2103c0442293439b44c1d8a59b714"
    },
    "tom": {
      "matchCount": 722,
      "source": "corsproxy.io",
      "success": true,
      "dataHash": "90fe883bfe931872111a858d99810955"
    }
  },
  "endTime": "2025-11-24T07:14:55.607Z",
  "duration": 1329
}