{
  "startTime": "2025-12-04T11:12:29.610Z",
  "professional": true,
  "updated": [
    "sarah",
    "tom"
  ],
  "failed": [
    "wendy"
  ],
  "skipped": [],
  "details": {
    "sarah": {
      "success": true,
      "matchCount": 361,
      "source": "corsproxy.io",
      "dataHash": "40309f64f5bd51ff9c86221940d99d97",
      "backup": null
    },
    "tom": {
      "success": true,
      "matchCount": 976,
      "source": "corsproxy.io",
      "dataHash": "c916c62a1f2fc8db6715fdcfd63934dc",
      "backup": "tom-data-1764846749615.json"
    },
    "wendy": {
      "success": false,
      "error": "HTTP 500",
      "restored": false,
      "recoveryDetails": null,
      "circuitBreaker": {
        "state": "CLOSED",
        "failures": 1,
        "lastFailure": "2025-12-04T11:12:31.056Z"
      }
    }
  },
  "circuitBreakers": {
    "tom": {
      "state": "CLOSED",
      "failures": 0,
      "lastFailure": null
    },
    "sarah": {
      "state": "CLOSED",
      "failures": 0,
      "lastFailure": null
    },
    "wendy": {
      "state": "CLOSED",
      "failures": 0,
      "lastFailure": null
    }
  },
  "integrity": {
    "totalAttempted": 3,
    "successful": 2,
    "failed": 1,
    "recovered": 0
  },
  "endTime": "2025-12-04T11:12:31.310Z",
  "duration": 1700
}