{
  "startTime": "2025-11-27T18:03:49.234Z",
  "updated": [
    "sarah",
    "tom"
  ],
  "failed": [
    "wendy"
  ],
  "skipped": [],
  "details": {
    "wendy": {
      "success": false,
      "error": "HTTP 404",
      "circuitBreakerState": "CLOSED",
      "restored": true
    },
    "sarah": {
      "matchCount": 580,
      "source": "corsproxy.io",
      "success": true,
      "dataHash": "78dc1c06f7457782d501ac83e42ef3d7"
    },
    "tom": {
      "matchCount": 1327,
      "source": "corsproxy.io",
      "success": true,
      "dataHash": "13ada9fed29e298f8b285a2b290da269"
    }
  },
  "endTime": "2025-11-27T18:03:50.074Z",
  "duration": 840
}