{
  "startTime": "2026-02-07T23:31:08.827Z",
  "strategy": "separated-endpoints",
  "updated": [
    "tom",
    "sarah",
    "wendy"
  ],
  "failed": [],
  "skipped": [],
  "details": {
    "tom": {
      "success": true,
      "matchCount": 187,
      "source": "worker-combined"
    },
    "sarah": {
      "success": true,
      "matchCount": 220,
      "source": "worker-combined"
    },
    "wendy": {
      "success": true,
      "matchCount": 530,
      "source": "worker-combined"
    }
  },
  "circuitBreakers": {
    "tom": {
      "state": "CLOSED",
      "failures": 0,
      "lastFailure": null
    },
    "sarah": {
      "state": "CLOSED",
      "failures": 0,
      "lastFailure": null
    },
    "wendy": {
      "state": "CLOSED",
      "failures": 0,
      "lastFailure": null
    }
  },
  "integrity": {
    "totalAttempted": 3,
    "successful": 3,
    "failed": 0,
    "recovered": 0
  },
  "endTime": "2026-02-07T23:31:19.184Z",
  "duration": 10357
}